sqlalchemy_easy_softdelete/__init__.py
sqlalchemy_easy_softdelete/hook.py
sqlalchemy_easy_softdelete/mixin.py
sqlalchemy_easy_softdelete/py.typed
sqlalchemy_easy_softdelete/handler/__init__.py
sqlalchemy_easy_softdelete/handler/sqlalchemy_easy_softdelete.py
sqlalchemy_easy_softdelete/handler/rewriter/__init__.py
sqlalchemy_easy_softdelete-0.9.0.dist-info/METADATA
sqlalchemy_easy_softdelete-0.9.0.dist-info/WHEEL
sqlalchemy_easy_softdelete-0.9.0.dist-info/licenses/LICENSE
sqlalchemy_easy_softdelete-0.9.0.dist-info/RECORD
