Metadata-Version: 2.4
Name: sqlalchemy-easy-softdelete
Version: 0.9.0
Summary: Easily add soft-deletion to your SQLAlchemy Models.
Project-URL: homepage, https://github.com/flipbit03/sqlalchemy-easy-softdelete
Project-URL: source, https://github.com/flipbit03/sqlalchemy-easy-softdelete
Project-URL: issues, https://github.com/flipbit03/sqlalchemy-easy-softdelete/issues
Author-email: Cadu <cadu.coelho@gmail.com>
License-Expression: BSD-3-Clause
License-File: LICENSE
Classifier: Development Status :: 5 - Production/Stable
Classifier: Intended Audience :: Developers
Classifier: License :: OSI Approved :: BSD License
Classifier: Natural Language :: English
Classifier: Programming Language :: Python :: 3.10
Classifier: Programming Language :: Python :: 3.11
Classifier: Programming Language :: Python :: 3.12
Classifier: Programming Language :: Python :: 3.13
Classifier: Programming Language :: Python :: 3.14
Classifier: Typing :: Typed
Requires-Python: >=3.10
Requires-Dist: sqlalchemy<2.1,>=1.4
